devicewwn/__init__.py
devicewwn/factory.py
devicewwn/wwn.py
devicewwn/manufacturers/__init__.py
devicewwn/manufacturers/EMC/Symmetrix.py
devicewwn/manufacturers/EMC/Vnx.py
devicewwn/manufacturers/EMC/Vplex.py
devicewwn/manufacturers/EMC/__init__.py
devicewwn/manufacturers/IBM/NPIV.py
devicewwn/manufacturers/IBM/__init__.py
devicewwn/manufacturers/NetApp/NetApp.py
devicewwn/manufacturers/NetApp/__init__.py
devicewwn-0.6.3.dist-info/DESCRIPTION.rst
devicewwn-0.6.3.dist-info/METADATA
devicewwn-0.6.3.dist-info/RECORD
devicewwn-0.6.3.dist-info/WHEEL
devicewwn-0.6.3.dist-info/metadata.json
devicewwn-0.6.3.dist-info/top_level.txt
