Metadata-Version: 2.0
Name: devicewwn
Version: 0.6.3
Summary: Manipulating Fibre Channel WWN easily with decoding capabilities
Home-page: http://github.com/jbrt/devicewwn
Author: Julien B.
Author-email: julien@toshokan.fr
License: GPLv3
Keywords: WWN SAN storage EMC Symmetrix VMAX NetApp Fibre Channel
Platform: UNKNOWN
Classifier: Development Status :: 5 - Production/Stable
Classifier: Programming Language :: Python :: 3
Classifier: Programming Language :: Python :: 3.1
Classifier: Programming Language :: Python :: 3.2
Classifier: Programming Language :: Python :: 3.3
Classifier: Programming Language :: Python :: 3.4
Classifier: Programming Language :: Python :: 3.5
Classifier: Topic :: Utilities
Classifier: License :: OSI Approved :: GNU General Public License v3 (GPLv3)
